scripts/eth-sdk.py
eth_python_sdk-0.0.1.dist-info/entry_points.txt
eth_python_sdk-0.0.1.dist-info/WHEEL
eth_python_sdk-0.0.1.dist-info/METADATA
eth_python_sdk-0.0.1.dist-info/RECORD
